poisson_CNN/__init__.py
poisson_CNN/blocks/__init__.py
poisson_CNN/blocks/bottleneck_block.py
poisson_CNN/blocks/metalearning_bottleneck_block.py
poisson_CNN/blocks/metalearning_resnet.py
poisson_CNN/blocks/resnet.py
poisson_CNN/blocks/subdomain_spp_block.py
poisson_CNN/dataset/__init__.py
poisson_CNN/dataset/generators/__init__.py
poisson_CNN/dataset/generators/analytical.py
poisson_CNN/dataset/generators/numerical.py
poisson_CNN/dataset/generators/reverse.py
poisson_CNN/dataset/generators/reverse_neumann.py
poisson_CNN/dataset/solvers/__init__.py
poisson_CNN/dataset/solvers/cholesky.py
poisson_CNN/dataset/solvers/multigrid.py
poisson_CNN/dataset/utils/__init__.py
poisson_CNN/dataset/utils/assign_to_tensor_index.py
poisson_CNN/dataset/utils/build_fd_coefficients.py
poisson_CNN/dataset/utils/compute_domain_sizes.py
poisson_CNN/dataset/utils/equal_split_tensor_slice.py
poisson_CNN/dataset/utils/flip_and_rotate_tensor.py
poisson_CNN/dataset/utils/generate_output_shapes_and_grid_spacings_from_aspect_ratios.py
poisson_CNN/dataset/utils/generate_smooth_function.py
poisson_CNN/dataset/utils/generate_uniformly_distributed_aspect_ratios.py
poisson_CNN/dataset/utils/get_fd_coefficients.py
poisson_CNN/dataset/utils/image_resize.py
poisson_CNN/dataset/utils/poisson_lhs_matrix.py
poisson_CNN/dataset/utils/set_max_magnitude.py
poisson_CNN/dataset/utils/slice_tf.py
poisson_CNN/dataset/utils/split_indices.py
poisson_CNN/layers/JacobiIterationLayer.py
poisson_CNN/layers/MergeWithAttention.py
poisson_CNN/layers/Scaling.py
poisson_CNN/layers/SpatialPyramidPool.py
poisson_CNN/layers/Upsample.py
poisson_CNN/layers/WeightedContractionLayer.py
poisson_CNN/layers/__init__.py
poisson_CNN/layers/deconvupscale.py
poisson_CNN/layers/metalearning_conv.py
poisson_CNN/layers/metalearning_deconvupscale.py
poisson_CNN/losses/__init__.py
poisson_CNN/losses/integral_loss.py
poisson_CNN/losses/loss_wrapper.py
poisson_CNN/losses/physics_informed_loss.py
poisson_CNN/misc/Boundary.py
poisson_CNN-0.3.0.dist-info/LICENSE
poisson_CNN-0.3.0.dist-info/METADATA
poisson_CNN-0.3.0.dist-info/WHEEL
poisson_CNN-0.3.0.dist-info/top_level.txt
poisson_CNN-0.3.0.dist-info/RECORD
