Metadata-Version: 2.1
Name: poisson-CNN
Version: 0.3.0
Summary: A convolutional neural network based Poisson solver
Home-page: https://github.com/aligirayhanozbay/poisson_CNN
Author: Ali Girayhan Ozbay
Author-email: aligirayhan.ozbay14@imperial.ac.uk
License: UNKNOWN
Platform: UNKNOWN
Classifier: Programming Language :: Python :: 3
Classifier: License :: OSI Approved :: GNU General Public License v3 or later (GPLv3+)
Classifier: Operating System :: OS Independent
Classifier: Topic :: Scientific/Engineering
Requires-Python: >=3.6
License-File: LICENSE
Requires-Dist: tensorflow
Requires-Dist: tensorflow-probability
Requires-Dist: pyamg
Requires-Dist: scipy
